qaznltk/__init__.py
qaznltk/qaznltk.py
qaznltk/vectorizer.py
qaznltk-1.2.4.4.dist-info/licenses/LICENSE
qaznltk-1.2.4.4.dist-info/METADATA
qaznltk-1.2.4.4.dist-info/WHEEL
qaznltk-1.2.4.4.dist-info/top_level.txt
qaznltk-1.2.4.4.dist-info/RECORD
