Metadata-Version: 2.4
Name: qaznltk
Version: 1.2.4.4
Summary: A package for working with Kazakh language text processing.
Author-email: "Aibol Zhussip, Kadyr Saparbay, Tair Ussen, Tuleuov Akhan & Arman Zhalgasbayev" <supwithproject@gmail.com>
Project-URL: Homepage, https://github.com/silvermete0r/QazNLTK
Project-URL: Bug Tracker, https://github.com/silvermete0r/QazNLTK/issues
Classifier: Programming Language :: Python :: 3
Classifier: License :: OSI Approved :: MIT License
Classifier: Operating System :: OS Independent
Requires-Python: >=3.8
License-File: LICENSE
Dynamic: license-file
